koruthos/__init__.py
koruthos/teste.py
koruthos-0.0.0.dist-info/METADATA
koruthos-0.0.0.dist-info/WHEEL
koruthos-0.0.0.dist-info/licenses/LICENSE
koruthos-0.0.0.dist-info/RECORD
